tests/__init__.py
tests/preprocess_test.py
weedout/__init__.py
weedout/datainfo.py
weedout/preprocess.py
weedout/visualization.py
weedout-1.1.dist-info/LICENSE
weedout-1.1.dist-info/METADATA
weedout-1.1.dist-info/WHEEL
weedout-1.1.dist-info/top_level.txt
weedout-1.1.dist-info/RECORD
