Metadata-Version: 2.1
Name: weedout
Version: 1.1
Summary: UNKNOWN
Home-page: UNKNOWN
License: UNKNOWN
Platform: UNKNOWN
Requires-Dist: pandas
Requires-Dist: numpy
Requires-Dist: seaborn
Requires-Dist: matplotlib
Requires-Dist: scikit-learn
Requires-Dist: statsmodels
Requires-Dist: imbalanced-learn
Requires-Dist: scipy
Requires-Dist: typing
